{
  "config": {
    "step": {
      "user": {
        "title": "Xenopixel Lightsaber",
        "description": "Select your Xenopixel lightsaber to set up.",
        "data": {
          "address": "Device"
        }
      },
      "bluetooth_confirm": {
        "title": "Xenopixel Lightsaber",
        "description": "Confirm setup of {name}"
      }
    },
    "abort": {
      "already_configured": "Device is already configured",
      "no_devices_found": "No Xenopixel lightsabers found. Make sure the saber is powered on and within Bluetooth range."
    }
  }
}
